Workbook
Name aporte: #REF!
Name patrimonio: [1]APP!$D$20
Name patrimonio: #REF!
Name qtd_anos: [1]APP!$D$18
Name qtd_anos: #REF!
Name rendimento_carteira: [1]APP!$D$13
Name rendimento_carteira: #REF!
Name sal: #REF!
Name salario: Simulador!$E$5
Name sug_invest: Simulador!$E$7
Name sugestao_investimento: #REF!
Name taxa_mensal: [1]APP!$D$19
Name taxa_mensal: #REF!

Sheet Simulador
C1: RDA INVEST
C2: SIMULADOR DE INVESTIMENTOS EM FUNDOS IMOBILIÁRIOS
C4: CONFIGURAÇÕES | G4: SIMULAÇÃO MENSAL
C5: Salário | G5: Quanto investir por mês
C6: Rendimento Carteira | G6: Por Quantos Anos | I6: 5
C7: Sugestão de Investimento (30%) | E7: =salario*30% -> 0 | G7: Taxa de Rendimento mensal | I7: 0.01079
G8: Patrimônio acumulado | I8: =FV(I7,I6*12,I5*-1) -> 0
C9: PERFIL DO INVESTIDOR | E9: Agressivo | G9: Dividendos Mensais | I9: =I8*E6 -> 0
C10: Aporte | E10: =I5 -> 0
C12: TIPO DE FII | D12: Percentual Sugerido | E12: Valores | G12: PROJEÇÃO DE CENÁRIOS | I12: DIVIDENDOS MENSAIS
C13: Desenvolvimento | D13: =VLOOKUP($E$9&"-"&$C13,Perfil!A:D,4,0) -> 0.5 | E13: =$D13*$E$10 -> 0 | F13: 2 | G13: Quanto em 2 Anos ? | H13: =FV($I$7,$F13*12,$I$5*-1) -> 0 | I13: =$H13*$E$6 -> 0
C14: FOFs | D14: =VLOOKUP($E$9&"-"&$C14,Perfil!A:D,4,0) -> 0.1 | E14: =$D14*$E$10 -> 0 | F14: 5 | G14: Quanto em 5 Anos ? | H14: =FV($I$7,$F14*12,$I$5*-1) -> 0 | I14: =$H14*$E$6 -> 0
C15: Híbridos | D15: =VLOOKUP($E$9&"-"&$C15,Perfil!A:D,4,0) -> 0.1 | E15: =$D15*$E$10 -> 0 | F15: 10 | G15: Quanto em 10 Anos ? | H15: =FV($I$7,$F15*12,$I$5*-1) -> 0 | I15: =$H15*$E$6 -> 0
C16: Hotelarias | D16: =VLOOKUP($E$9&"-"&$C16,Perfil!A:D,4,0) -> 0.05 | E16: =$D16*$E$10 -> 0 | F16: 15 | G16: Quanto em 15 Anos ? | H16: =FV($I$7,$F16*12,$I$5*-1) -> 0 | I16: =$H16*$E$6 -> 0
C17: Papel | D17: =VLOOKUP($E$9&"-"&$C17,Perfil!A:D,4,0) -> 0.1 | E17: =$D17*$E$10 -> 0 | F17: 20 | G17: Quanto em 20 Anos ? | H17: =FV($I$7,$F17*12,$I$5*-1) -> 0 | I17: =$H17*$E$6 -> 0
C18: Tijolo | D18: =VLOOKUP($E$9&"-"&$C18,Perfil!A:D,4,0) -> 0.15 | E18: =$D18*$E$10 -> 0 | F18: 30 | G18: Quanto em 30 Anos ? | H18: =FV($I$7,$F18*12,$I$5*-1) -> 0 | I18: =$H18*$E$6 -> 0
G20: EVOLUÇÃO PATRIMONIAL

Sheet Perfil
A2: CHAVE | B2: PERFIL | C2: TIPO DE FII | D2: % | F2: PERFIL
A3: =B3&"-"&C3 -> Conservador-Desenvolvimento | B3: Conservador | C3: Desenvolvimento | D3: 0.25 | F3: Conservador
A4: =B4&"-"&C4 -> Conservador-FOFs | B4: Conservador | C4: FOFs | D4: 0.3 | F4: Moderado
A5: =B5&"-"&C5 -> Conservador-Híbridos | B5: Conservador | C5: Híbridos | D5: 0.1 | F5: Agressivo
A6: =B6&"-"&C6 -> Conservador-Hotelarias | B6: Conservador | C6: Hotelarias | D6: 0.05
A7: =B7&"-"&C7 -> Conservador-Papel | B7: Conservador | C7: Papel | D7: 0.2
A8: =B8&"-"&C8 -> Conservador-Tijolo | B8: Conservador | C8: Tijolo | D8: 0.1
A9: =B9&"-"&C9 -> Moderado-Desenvolvimento | B9: Moderado | C9: Desenvolvimento | D9: 0.32
A10: =B10&"-"&C10 -> Moderado-FOFs | B10: Moderado | C10: FOFs | D10: 0.35
A11: =B11&"-"&C11 -> Moderado-Híbridos | B11: Moderado | C11: Híbridos | D11: 0.08
A12: =B12&"-"&C12 -> Moderado-Hotelarias | B12: Moderado | C12: Hotelarias | D12: 0.05
A13: =B13&"-"&C13 -> Moderado-Papel | B13: Moderado | C13: Papel | D13: 0.1
A14: =B14&"-"&C14 -> Moderado-Tijolo | B14: Moderado | C14: Tijolo | D14: 0.1
A15: =B15&"-"&C15 -> Agressivo-Desenvolvimento | B15: Agressivo | C15: Desenvolvimento | D15: 0.5
A16: =B16&"-"&C16 -> Agressivo-FOFs | B16: Agressivo | C16: FOFs | D16: 0.1
A17: =B17&"-"&C17 -> Agressivo-Híbridos | B17: Agressivo | C17: Híbridos | D17: 0.1
... A20: =B20&"-"&C20 -> Agressivo-Tijolo | B20: Agressivo | C20: Tijolo | D20: 0.15
